sabathdev/__init__.py
sabathdev/__main__.py
sabathdev-0.1.dist-info/METADATA
sabathdev-0.1.dist-info/WHEEL
sabathdev-0.1.dist-info/top_level.txt
sabathdev-0.1.dist-info/RECORD
